macmon/__init__.py
macmon/core.py
macmon/bin/LICENSE
macmon/bin/macmon
macmon/bin/readme.md
macmon_python-0.1.2.dist-info/licenses/LICENSE
macmon_python-0.1.2.dist-info/METADATA
macmon_python-0.1.2.dist-info/WHEEL
macmon_python-0.1.2.dist-info/entry_points.txt
macmon_python-0.1.2.dist-info/top_level.txt
macmon_python-0.1.2.dist-info/RECORD
